sas/__init__.py
sas/storage/__init__.py
sas/storage/shared_config.py
sas/storage/blob/__init__.py
sas/storage/blob/async_helper.py
sas/storage/blob/config.py
sas/storage/blob/helper.py
sas/storage/queue/__init__.py
sas/storage/queue/async_helper.py
sas/storage/queue/helper.py
sas_storage-1.0.0.dist-info/licenses/LICENSE
sas_storage-1.0.0.dist-info/METADATA
sas_storage-1.0.0.dist-info/WHEEL
sas_storage-1.0.0.dist-info/top_level.txt
sas_storage-1.0.0.dist-info/RECORD
