Metadata-Version: 2.4
Name: sas-storage
Version: 1.0.0
Summary: A comprehensive Python helper for Azure Storage Blob and Queue operations with file explorer-like functionality
Author-email: DB Lee <db.lee@microsoft.com>
License-Expression: MIT
Project-URL: Homepage, https://github.com/mcaps-microsoft/python_storageaccount_helper
Project-URL: Repository, https://github.com/mcaps-microsoft/python_storageaccount_helper
Project-URL: Documentation, https://github.com/mcaps-microsoft/python_storageaccount_helper/blob/main/README.md
Project-URL: Bug Reports, https://github.com/mcaps-microsoft/python_storageaccount_helper/issues
Keywords: azure,blob,storage,cloud,file-explorer,sas,queue
Classifier: Development Status :: 4 - Beta
Classifier: Intended Audience :: Developers
Classifier: Programming Language :: Python :: 3
Classifier: Programming Language :: Python :: 3.12
Classifier: Topic :: Software Development :: Libraries :: Python Modules
Classifier: Topic :: System :: Filesystems
Requires-Python: >=3.12
License-File: LICENSE
Requires-Dist: azure-storage-blob>=12.20.0
Requires-Dist: azure-storage-queue>=12.9.0
Requires-Dist: azure-identity>=1.15.0
Requires-Dist: azure-core>=1.29.0
Requires-Dist: python-dotenv>=1.1.1
Requires-Dist: aiofiles>=23.2.0
Requires-Dist: asyncio-mqtt>=0.16.0
Requires-Dist: aiohttp>=3.8.0
Provides-Extra: dev
Requires-Dist: pytest>=7.0.0; extra == "dev"
Requires-Dist: pytest-cov>=4.0.0; extra == "dev"
Requires-Dist: pytest-asyncio>=0.21.0; extra == "dev"
Requires-Dist: black>=22.0.0; extra == "dev"
Requires-Dist: flake8>=4.0.0; extra == "dev"
Requires-Dist: mypy>=0.991; extra == "dev"
Provides-Extra: docs
Requires-Dist: sphinx>=4.0.0; extra == "docs"
Requires-Dist: sphinx-rtd-theme>=1.0.0; extra == "docs"
Dynamic: license-file
